pydantic_neomodel_dict/__init__.py
pydantic_neomodel_dict/errors.py
pydantic_neomodel_dict/py.typed
pydantic_neomodel_dict/converters/__init__.py
pydantic_neomodel_dict/converters/_base_converter.py
pydantic_neomodel_dict/converters/async_converter.py
pydantic_neomodel_dict/converters/sync_converter.py
pydantic_neomodel_dict/core/__init__.py
pydantic_neomodel_dict/core/hooks.py
pydantic_neomodel_dict/core/registry.py
pydantic_neomodel_dict/io/__init__.py
pydantic_neomodel_dict/io/_common.py
pydantic_neomodel_dict/io/async_io.py
pydantic_neomodel_dict/io/sync_io.py
pydantic_neomodel_dict-0.4.2.dist-info/licenses/LICENSE
pydantic_neomodel_dict-0.4.2.dist-info/METADATA
pydantic_neomodel_dict-0.4.2.dist-info/WHEEL
pydantic_neomodel_dict-0.4.2.dist-info/top_level.txt
pydantic_neomodel_dict-0.4.2.dist-info/RECORD
