Metadata-Version: 2.4
Name: pydantic-neomodel-dict
Version: 0.4.2
Summary: A bidirectional converter between Pydantic models, Python dictionaries and Neomodel (Neo4j) OGM models with async support
Author-email: Max Azatian <max.azatian@gmail.com>
License: MIT
Project-URL: Homepage, https://github.com/HardMax71/pydantic-neomodel-dict
Project-URL: Bug Tracker, https://github.com/HardMax71/pydantic-neomodel-dict/issues
Project-URL: Documentation, https://github.com/HardMax71/pydantic-neomodel-dict#readme
Keywords: pydantic,neomodel,neo4j,orm,converter,ogm
Classifier: Programming Language :: Python :: 3
Classifier: Programming Language :: Python :: 3.10
Classifier: Programming Language :: Python :: 3.11
Classifier: Programming Language :: Python :: 3.12
Classifier: License :: OSI Approved :: MIT License
Classifier: Operating System :: OS Independent
Classifier: Topic :: Database
Classifier: Topic :: Software Development :: Libraries :: Python Modules
Classifier: Intended Audience :: Developers
Requires-Python: <3.13,>=3.10
License-File: LICENSE
Requires-Dist: pydantic>=2.0.0
Requires-Dist: neomodel>=5.0.0
Provides-Extra: dev
Requires-Dist: pytest>=8.0.0; extra == "dev"
Requires-Dist: pytest-cov>=4.0.0; extra == "dev"
Requires-Dist: hypothesis>=6.0.0; extra == "dev"
Requires-Dist: mypy>=1.0.0; extra == "dev"
Requires-Dist: ruff>=0.9.0; extra == "dev"
Dynamic: license-file
